kstlib/__init__.py
kstlib/__main__.py
kstlib/kstlib.conf.yml
kstlib/limits.py
kstlib/meta.py
kstlib/py.typed
kstlib/ssl.py
kstlib/alerts/__init__.py
kstlib/alerts/exceptions.py
kstlib/alerts/manager.py
kstlib/alerts/models.py
kstlib/alerts/throttle.py
kstlib/alerts/channels/__init__.py
kstlib/alerts/channels/base.py
kstlib/alerts/channels/email.py
kstlib/alerts/channels/slack.py
kstlib/auth/__init__.py
kstlib/auth/callback.py
kstlib/auth/config.py
kstlib/auth/errors.py
kstlib/auth/models.py
kstlib/auth/session.py
kstlib/auth/token.py
kstlib/auth/providers/__init__.py
kstlib/auth/providers/base.py
kstlib/auth/providers/oauth2.py
kstlib/auth/providers/oidc.py
kstlib/cache/__init__.py
kstlib/cache/decorator.py
kstlib/cache/strategies.py
kstlib/cli/__init__.py
kstlib/cli/app.py
kstlib/cli/common.py
kstlib/cli/commands/__init__.py
kstlib/cli/commands/config.py
kstlib/cli/commands/auth/__init__.py
kstlib/cli/commands/auth/common.py
kstlib/cli/commands/auth/login.py
kstlib/cli/commands/auth/logout.py
kstlib/cli/commands/auth/providers.py
kstlib/cli/commands/auth/status.py
kstlib/cli/commands/auth/token.py
kstlib/cli/commands/auth/whoami.py
kstlib/cli/commands/ops/__init__.py
kstlib/cli/commands/ops/attach.py
kstlib/cli/commands/ops/common.py
kstlib/cli/commands/ops/list_sessions.py
kstlib/cli/commands/ops/logs.py
kstlib/cli/commands/ops/start.py
kstlib/cli/commands/ops/status.py
kstlib/cli/commands/ops/stop.py
kstlib/cli/commands/rapi/__init__.py
kstlib/cli/commands/rapi/call.py
kstlib/cli/commands/rapi/list.py
kstlib/cli/commands/rapi/show.py
kstlib/cli/commands/secrets/__init__.py
kstlib/cli/commands/secrets/common.py
kstlib/cli/commands/secrets/decrypt.py
kstlib/cli/commands/secrets/doctor.py
kstlib/cli/commands/secrets/encrypt.py
kstlib/cli/commands/secrets/shred.py
kstlib/config/__init__.py
kstlib/config/exceptions.py
kstlib/config/export.py
kstlib/config/loader.py
kstlib/config/sops.py
kstlib/db/__init__.py
kstlib/db/aiosqlcipher.py
kstlib/db/cipher.py
kstlib-1.0.2.dist-info/licenses/LICENSE.md
kstlib-1.0.2.dist-info/METADATA
kstlib-1.0.2.dist-info/WHEEL
kstlib-1.0.2.dist-info/entry_points.txt
kstlib-1.0.2.dist-info/top_level.txt
kstlib-1.0.2.dist-info/RECORD
