Metadata-Version: 2.4
Name: kstlib
Version: 1.0.2
Summary: Config-driven helpers for Python projects (dynamic config, secure secrets, preset logging, and more…)
Author-email: Michel TRUONG <michel.truong@gmail.com>
Maintainer-email: Michel TRUONG <michel.truong@gmail.com>
License-Expression: MIT
Project-URL: Homepage, https://github.com/KaminoU/kstlib
Project-URL: Repository, https://github.com/KaminoU/kstlib
Project-URL: Bug Tracker, https://github.com/KaminoU/kstlib/issues
Project-URL: Changelog, https://github.com/KaminoU/kstlib/blob/main/CHANGELOG.md
Keywords: kstlib
Classifier: Development Status :: 5 - Production/Stable
Classifier: Intended Audience :: Developers
Classifier: Programming Language :: Python :: 3
Classifier: Programming Language :: Python :: 3.10
Classifier: Programming Language :: Python :: 3.11
Classifier: Programming Language :: Python :: 3.12
Classifier: Programming Language :: Python :: 3.13
Classifier: Programming Language :: Python :: 3.14
Requires-Python: >=3.10
License-File: LICENSE.md
Requires-Dist: pyyaml<7,>=6.0
Requires-Dist: tomli<3,>=2.3
Requires-Dist: tomli-w<2,>=1.0
Requires-Dist: python-box<8,>=7.3
Requires-Dist: typer<1,>=0.19
Requires-Dist: click<9,>=8.3
Requires-Dist: rich<15,>=14.2
Requires-Dist: structlog<26,>=25.0
Requires-Dist: aiosqlite<1,>=0.21
Requires-Dist: aiosmtplib<5,>=4.0
Requires-Dist: websockets<16,>=15.0
Requires-Dist: jinja2<4,>=3.1
Requires-Dist: humanize<5,>=4.11
Requires-Dist: httpx<1,>=0.28
Requires-Dist: authlib<2,>=1.5
Requires-Dist: pendulum<4,>=3.0
Provides-Extra: dev
Requires-Dist: pytest<9,>=8.4; extra == "dev"
Requires-Dist: pytest-cov<8,>=7.0; extra == "dev"
Requires-Dist: pytest-asyncio<2,>=1.2; extra == "dev"
Requires-Dist: ruff<1,>=0.14; extra == "dev"
Requires-Dist: mypy<2,>=1.18; extra == "dev"
Requires-Dist: types-PyYAML<7,>=6.0; extra == "dev"
Requires-Dist: pre-commit<5,>=4.0; extra == "dev"
Requires-Dist: boto3<2,>=1.35; extra == "dev"
Provides-Extra: db-crypto
Requires-Dist: sqlcipher3<1,>=0.5; extra == "db-crypto"
Provides-Extra: docs
Requires-Dist: sphinx<9,>=8.1; extra == "docs"
Requires-Dist: furo<2026,>=2025.9; extra == "docs"
Requires-Dist: myst-parser<5,>=4.0; extra == "docs"
Requires-Dist: sphinx-autodoc-typehints<4,>=3.0; extra == "docs"
Requires-Dist: sphinx-togglebutton<1,>=0.3; extra == "docs"
Requires-Dist: sphinx-design<0.7,>=0.6; extra == "docs"
Provides-Extra: build
Requires-Dist: build<2,>=1.3; extra == "build"
Requires-Dist: twine<7,>=6.2; extra == "build"
Provides-Extra: tox
Requires-Dist: tox<5,>=4.31; extra == "tox"
Provides-Extra: infra-tools
Requires-Dist: awscli-local<1,>=0.22; extra == "infra-tools"
Provides-Extra: textual
Requires-Dist: textual<7,>=6.3; extra == "textual"
Provides-Extra: all
Requires-Dist: pytest<9,>=8.4; extra == "all"
Requires-Dist: pytest-cov<8,>=7.0; extra == "all"
Requires-Dist: pytest-asyncio<2,>=1.2; extra == "all"
Requires-Dist: ruff<1,>=0.14; extra == "all"
Requires-Dist: mypy<2,>=1.18; extra == "all"
Requires-Dist: types-PyYAML<7,>=6.0; extra == "all"
Requires-Dist: sphinx<9,>=8.1; extra == "all"
Requires-Dist: furo<2026,>=2025.9; extra == "all"
Requires-Dist: myst-parser<5,>=4.0; extra == "all"
Requires-Dist: sphinx-autodoc-typehints<4,>=3.0; extra == "all"
Requires-Dist: sphinx-togglebutton<1,>=0.3; extra == "all"
Requires-Dist: sphinx-design<0.7,>=0.6; extra == "all"
Requires-Dist: build<2,>=1.3; extra == "all"
Requires-Dist: twine<7,>=6.2; extra == "all"
Requires-Dist: tox<5,>=4.31; extra == "all"
Requires-Dist: pre-commit<5,>=4.0; extra == "all"
Requires-Dist: boto3<2,>=1.35; extra == "all"
Requires-Dist: awscli-local<1,>=0.22; extra == "all"
Dynamic: license-file
